compound_split/__init__.py
compound_split/char_split.py
compound_split/char_split_train.py
compound_split/de_ngram_probs.py
compound_split/doc_client.py
compound_split/doc_config.py
compound_split/doc_server.py
compound_split/doc_split.py
compound_split/doc_test.py
compound_split/nl_ngram_probs.py
compound_split/dicts/de-misc.dic
compound_split/dicts/de-mixed.dic
compound_split/dicts/nl-NL.dic
compound_split-1.0.2.dist-info/LICENSE
compound_split-1.0.2.dist-info/METADATA
compound_split-1.0.2.dist-info/WHEEL
compound_split-1.0.2.dist-info/top_level.txt
compound_split-1.0.2.dist-info/RECORD
