Metadata-Version: 2.1
Name: compound-split
Version: 1.0.2
Summary: Splits a compound into its body and head. So far German and Dutch are supported.
Home-page: https://github.com/JoelNiklaus/CompoundSplit
Author: Don Tuggener
Author-email: don.tuggener@gmail.com
Maintainer: Joel Niklaus
Maintainer-email: me@joelniklaus.ch
License: GPL-3.0 License
Platform: UNKNOWN
Classifier: Programming Language :: Python :: 3
Classifier: License :: OSI Approved :: GNU General Public License v3 (GPLv3)
Classifier: Operating System :: OS Independent
Requires-Python: >=3
